LICENSE
MANIFEST.in
README.md
pyproject.toml
setup.py
fitbit_cli/__init__.py
fitbit_cli/cli.py
fitbit_cli/exceptions.py
fitbit_cli/fitbit_api.py
fitbit_cli/fitbit_setup.py
fitbit_cli/formatter.py
fitbit_cli/main.py
fitbit_cli.egg-info/PKG-INFO
fitbit_cli.egg-info/SOURCES.txt
fitbit_cli.egg-info/dependency_links.txt
fitbit_cli.egg-info/entry_points.txt
fitbit_cli.egg-info/requires.txt
fitbit_cli.egg-info/top_level.txt
tests/cli_test.py