Metadata-Version: 2.4
Name: fitbit-cli
Version: 1.5.1
Summary: Access your Fitbit data at your terminal.
Home-page: https://github.com/veerendra2/fitbit-cli
Download-URL: https://github.com/veerendra2/fitbit-cli/archive/1.5.1.tar.gz
Author: veerendra2
Author-email: vk.tyk23@simplelogin.com
License: MIT
Project-URL: Documentation, https://github.com/veerendra2/fitbit-cli
Keywords: fitbit,fitbit-api,cli,python
Classifier: Development Status :: 5 - Production/Stable
Classifier: Intended Audience :: End Users/Desktop
Classifier: License :: OSI Approved :: Apache Software License
Classifier: Natural Language :: English
Classifier: Operating System :: MacOS
Classifier: Operating System :: POSIX :: Linux
Classifier: Programming Language :: Python :: 3 :: Only
Classifier: Programming Language :: Python :: 3.12
Classifier: Programming Language :: Python :: 3.13
Classifier: Programming Language :: Python :: 3.9
Classifier: Programming Language :: Python :: 3
Classifier: Programming Language :: Python
Classifier: Topic :: Utilities
Requires-Python: >=3.9
License-File: LICENSE
Requires-Dist: requests==2.32.5
Requires-Dist: rich==14.2.0
Dynamic: author
Dynamic: author-email
Dynamic: classifier
Dynamic: description
Dynamic: description-content-type
Dynamic: download-url
Dynamic: home-page
Dynamic: keywords
Dynamic: license
Dynamic: license-file
Dynamic: project-url
Dynamic: requires-dist
Dynamic: requires-python
Dynamic: summary
